{"url": "https://ew.com/tv/2017/05/15/this-is-us-season-2-trailer-fans/", "text": "Fall TV This Is Us type TV Show Network NBC Genre Drama\n\nIt is indisputable that This Is Us left its mark the TV landscape this past season, emerging as broadcast TV\u2019s big new breakout. The facts \u2014 and oodles of social media comments \u2014 also have shown that this high-octane family dramedy has deeply affected fans, to the point of tears.\n\nOn Monday, NBC has released its first teaser in anticipation of season 2 \u2014 there\u2019s no new footage, as production on the new episodes hasn\u2019t begun \u2014 and in the emotionally charged spot, real-life fans gush about the impact that the Pearson clan has had on them. (For example, one named her daughter after Chrissy Metz\u2019s Kate.) But these viewers are in for another twist, as This Is Us stars Milo Ventimiglia, Mandy Moore, Sterling K. Brown, and Metz surprise them mid-testimonial. You can see the shock and awe that results from these encounters in the footage above.\n\nThis Is Us returns this fall, but on a new night: Thursday.\n\nTo read what Milo Ventimiglia had to say about the season 1 finale, click here.", "images": ["https://ewedit.files.wordpress.com/2019/04/nup_186112_0385.jpg", "https://ewedit.files.wordpress.com/2019/03/nup_185863_0033.jpg", "https://ew.com/img/streaming/hulu.png", "https://ewedit.files.wordpress.com/2019/11/nup_188719_0097.jpg", "data:image/svg+xml,%3Csvg%20xmlns='http://www.w3.org/2000/svg'%20viewBox='0%200%20100%20100'%3E%3C/svg%3E", "https://ewedit.files.wordpress.com/2018/11/nup_184748_1103.jpg?crop=0px%2C0px%2C2700px%2C1417.5px&resize=1200%2C630", "https://ewedit.files.wordpress.com/2019/11/nup_188589_0140.jpg", "https://ewedit.files.wordpress.com/2018/10/celebrity-binge.jpg?w=768", "https://ewedit.files.wordpress.com/2019/09/nup_187678_0020.jpg?crop=0px%2C145px%2C2700px%2C1419px&resize=1200%2C630", "https://secure.gravatar.com/avatar/602b73f362605bc89706a277f90e2fb1?s=300&d=blank&r=g", "https://ewedit.files.wordpress.com/2018/10/nup_184224_0695.jpg", "https://ewedit.files.wordpress.com/2019/01/nup_185055_0678.jpg", "https://ewedit.files.wordpress.com/2018/10/this-is-us-toby.jpg", "https://ewedit.files.wordpress.com/2019/10/this-is-us-1.jpg", "https://ewedit.files.wordpress.com/2019/10/this-is-us-4.jpg", "https://ewedit.files.wordpress.com/2017/05/this-is-us-fans-1.jpg?crop=0px%2C0px%2C2700px%2C1417.5px&resize=1200%2C630", "data:image/svg+xml,%3Csvg%20xmlns='http://www.w3.org/2000/svg'%20viewBox='0%200%20100%2064'%3E%3C/svg%3E", "https://ewedit.files.wordpress.com/2019/10/nup_188256_0602.jpg?crop=0px%2C0px%2C2700px%2C1417.5px&resize=1200%2C630", "https://ewedit.files.wordpress.com/2018/11/nup_184225_2559.jpg", "https://ewedit.files.wordpress.com/2019/11/this-is-us-split.jpg", "https://ewedit.files.wordpress.com/2018/11/nup_184411_0090.jpg", "https://ewedit.files.wordpress.com/2017/11/rolestout.jpg?w=768", "https://ewedit.files.wordpress.com/2017/09/lennykravitz.jpg?w=768", "https://ewedit.files.wordpress.com/2019/03/nup_185719_0148.jpg", "https://ewedit.files.wordpress.com/2019/10/nup_188410_1170.jpg?crop=0px%2C61px%2C2700px%2C1418px&resize=1200%2C630", "https://ewedit.files.wordpress.com/2019/02/nup_185326_0409.jpg", "https://ewedit.files.wordpress.com/2019/09/nup_187879_1237.jpg", "https://ewedit.files.wordpress.com/2019/03/nup_185862_1462.jpg", "https://ewedit.files.wordpress.com/2019/01/nup_184837_1322.jpg", "https://ewedit.files.wordpress.com/2019/02/nup_185371_2565-2.jpg", "https://ewedit.files.wordpress.com/2019/03/nup_185862_1462.jpg?crop=538px%2C18px%2C1645px%2C1646px&resize=150%2C150", "https://ewedit.files.wordpress.com/2019/03/nup_185702_0426.jpg"], "top_img": "https://ewedit.files.wordpress.com/2017/05/this-is-us-fans-1.jpg?crop=0px%2C0px%2C2700px%2C1417.5px&resize=1200%2C630", "keywords": [], "authors": ["Dan Snierson", "Amanda Ostuni", "David Canfield"], "canonical_link": "https://ew.com/tv/2017/05/15/this-is-us-season-2-trailer-fans/", "title": "This Is Us season 2 teaser shows the cast shocking fans", "meta_data": {"viewport": "width=device-width, initial-scale=1, maximum-scale=1, minimum-scale=1, user-scalable=no", "keywords": "This Is Us, Milo Ventimiglia, Mandy Moore, Chrissy Metz, Sterling K. Brown, Upfronts, NBC, NBC upfront", "news_keywords": "This Is Us, Milo Ventimiglia, Mandy Moore, Chrissy Metz, Sterling K. Brown, Upfronts, NBC, NBC upfront", "description": "The NBC family dramedy returns this fall", "og": {"title": "'This Is Us' Season 2 Teaser Shows the Cast Shocking Fans", "type": "article", "site_name": "EW.com", "url": "https://ew.com/tv/2017/05/15/this-is-us-season-2-trailer-fans/", "description": "It is indisputable that This Is Us left its mark the TV landscape this past season, emerging as broadcast TV\u2019s\u2026", "image": {"identifier": "https://ewedit.files.wordpress.com/2017/05/this-is-us-fans-1.jpg?crop=0px%2C0px%2C2700px%2C1417.5px&resize=1200%2C630", "width": 1200, "height": 630}}, "pinterest": {"url": "https://ew.com/tv/2017/05/15/this-is-us-season-2-trailer-fans/", "description": "The NBC family dramedy returns this fall", "media": "https://ewedit.files.wordpress.com/2017/05/this-is-us-fans-1.jpg?crop=0px%2C0px%2C2700px%2C1417.5px&resize=1200%2C630"}, "twitter": {"card": "summary_large_image", "url": "https://ew.com/tv/2017/05/15/this-is-us-season-2-trailer-fans/", "title": "'This Is Us' Season 2 Teaser Shows the Cast Shocking Fans", "description": "The NBC family dramedy returns this fall", "site": "@ew", "image": "https://ewedit.files.wordpress.com/2017/05/this-is-us-fans-1.jpg?crop=0px%2C0px%2C2700px%2C1417.5px&resize=1200%2C630"}, "fb": {"pages": 52150999700}, "article": {"opinion": "false"}}, "movies": [], "publish_date": 1494820800.0, "source": "https://ew.com", "summary": ""}